<?xml version="1.0" encoding="UTF-8"?><i><chatserver>chat.bilibili.com</chatserver><chatid>59186555</chatid><mission>0</mission><maxlimit>1000</maxlimit><state>0</state><real_name>0</real_name><source>k-v</source><d p="36.24800,4,25,16737792,1539505194,0,2aa8fa4e,6481782925950978">每天醒来 先检查自己身材</d><d p="38.59500,4,25,16737843,1539505210,0,2aa8fa4e,6481791296208896">太胖太瘦都不能被看出来</d><d p="47.93800,4,25,16737843,1539505244,0,2aa8fa4e,6481808752377860">真奇怪 好羡慕隔壁小白</d><d p="50.26400,4,25,16737843,1539505256,0,2aa8fa4e,6481815235198976">怎么我就总会被兄弟俩安排</d><d p="53.52400,4,25,16737843,1539505268,0,2aa8fa4e,6481821324279810">煮烤煎炸 偶尔还做个叫花</d><d p="56.01600,4,25,16737843,1539505277,0,2aa8fa4e,6481826520498176">吃鸡也不错 不如了解一下</d><d p="42.03100,4,25,16737843,1539505222,0,2aa8fa4e,6481797669978116">记得要乖 千万别互相伤害</d><d p="44.43100,4,25,16737843,1539505232,0,2aa8fa4e,6481802831069188">打架受伤被发现就得狗带</d><d p="59.50100,4,25,16737843,1539505327,0,2aa8fa4e,6481852596486144">打架受伤啦 来不及救啦</d><d p="61.66900,4,25,16737843,1539505339,0,2aa8fa4e,6481858751102978">说这话的 你良心不会痛吗</d><d p="70.40500,4,25,16737843,1539505379,0,2aa8fa4e,6481879576346624">（麻烦你啦）</d><d p="71.77300,4,25,16737843,1539505388,0,2aa8fa4e,6481884673998852">擦下口水吧</d><d p="65.33100,4,25,16737843,1539505350,0,2aa8fa4e,6481864605827072">吃的太多啦 快养不起啦</d><d p="67.51000,4,25,16737843,1539505360,0,2aa8fa4e,6481870028013568">确认过眼神 是你饿啦</d><d p="107.42900,4,25,16737843,1539505507,0,2aa8fa4e,6481947128758272">这只竹鼠 长那么大 最喜欢吃 吃得又多</d><d p="110.36400,4,25,16737843,1539505518,0,2aa8fa4e,6481952754892800">人家都没他长得快 还不如 把它 做成</d><d p="113.24200,4,25,16737843,1539505529,0,2aa8fa4e,6481958642122752">烤竹鼠 闷竹鼠 红烧鼠 叫花鼠 花菇炖鼠</d><d p="116.22800,4,25,16737843,1539505540,0,2aa8fa4e,6481964162875394">中暑 淋雨 再这样下去的话 肯定吃不消的</d><d p="122.16900,4,25,16737843,1539505564,0,2aa8fa4e,6481976812371972">它 三天都没吃 现在都瘦了 还不如加点</d><d p="125.26700,4,25,16737843,1539505575,0,2aa8fa4e,6481982263918594">生姜 八角 生抽 白酒 嫩竹子 大蒜 孜然 鸭子</d><d p="128.23100,4,25,16737843,1539505584,0,2aa8fa4e,6481987118825476">想吃个竹鼠都有点难啊</d><d p="119.16800,4,25,16737843,1539505554,0,2aa8fa4e,6481971406438404">你看这只公鼠 本来是一公一母 那个母的 下崽了</d><d p="133.18600,4,25,16737843,1539505628,0,2aa8fa4e,6482010395115520">怎么我就总会被兄弟俩 安排</d><d p="136.44500,4,25,16737843,1539505638,0,2aa8fa4e,6482015774310404">煮烤煎炸 偶尔还做个叫花</d><d p="138.95300,4,25,16737843,1539505648,0,2aa8fa4e,6482020912857090">吃鸡也不错 不如了解一下</d><d p="130.88000,4,25,16737843,1539505619,0,2aa8fa4e,6482005574811650">真奇怪 好羡慕隔壁小白</d><d p="148.20600,4,25,16737843,1539505707,0,2aa8fa4e,6482051586850818">难得没病啊 你却失望啦</d><d p="150.29000,4,25,16737843,1539505717,0,2aa8fa4e,6482057076670468">反正理由 现编就好啦</d><d p="142.29500,4,25,16737843,1539505681,0,2aa8fa4e,6482037840019458">中暑软趴趴 忧郁症瘦啦</d><d p="144.50900,4,25,16737843,1539505691,0,2aa8fa4e,6482043280031748">看不出的 内伤你认真的吗</d><d p="153.31000,4,25,16737843,1539505742,0,2aa8fa4e,6482070336438272">（啊？想到了？）</d><d p="154.42400,4,25,16737843,1539505755,0,2aa8fa4e,6482077088743424">随便你了啦！</d><d p="3.35000,1,25,16777215,1539486206,0,148f4df8,6471827617480706">不忍心用弹幕打破气氛</d><d p="12.94700,1,25,16777215,1539486210,0,8bf3f848,6471829802188800">15好</d><d p="29.13000,1,25,16777215,1539486250,0,d00c20e2,6471850662035458">什么鬼哈哈哈哈哈</d><d p="139.48900,1,25,16777215,1539486397,0,d00c20e2,6471927816781826">又疯了一个hhhhh</d><d p="95.56300,1,25,16777215,1539486792,0,f1dcbbe6,6472135079362562">好可爱(/ω＼)</d><d p="126.65900,1,25,16777215,1539487972,0,5313d495,6472753731338240">hhhhh</d><d p="1.59200,1,25,16777215,1539489744,0,cd679fc2,6473682404769792">哇</d><d p="5.21900,1,25,16777215,1539492817,0,74185fe1,6475293705371648">再来一遍</d><d p="64.44800,1,25,16777215,1539494777,0,8e3dfae4,6476321171439616">好可爱WWW</d><d p="7.22500,1,25,16777215,1539496824,0,4f8d054,6477394351226880">啊啊啊啊啊可爱</d><d p="77.49700,1,25,16777215,1539500855,0,a4c4740,6479508107952130">12</d><d p="26.82200,1,25,16777215,1539500833,0,31b52b89,6479496522760196">小猪！</d><d p="72.73800,1,25,16777215,1539501128,0,948c1766,6479650834350080">好听！</d><d p="78.79900,1,25,16777215,1539502071,0,6800a12a,6480145574526976">好听</d><d p="67.55900,1,25,16777215,1539502224,0,3c97432e,6480225685733376">好可爱啊哈哈哈哈</d><d p="101.97300,1,25,16777215,1539502344,0,883132ae,6480288426229762">前方高萌预警，非战斗人员请撤离！注意这不是演习！</d><d p="12.59900,1,25,16777215,1539503694,0,8b22f6da,6480996327751684">再来一遍</d><d p="152.63700,1,25,16777215,1539504252,0,957ce60f,6481288729985026">嗯这调音师不错</d><d p="72.31300,1,25,16777215,1539504485,0,6467b2b8,6481411094609920">不一样的萌点！</d><d p="85.27400,1,25,16777215,1539504680,0,eb8ebfdf,6481513045557248">43</d><d p="52.16000,1,25,16777215,1539509984,0,c00873d,6484294271762436">好听！好听！</d><d p="55.10200,1,25,16777215,1539511428,0,5f6c0054,6485051354120192">哈哈哈</d><d p="78.45700,1,25,16777215,1539513244,0,3adbd59e,6486003329531904">这只竹鼠中暑了，煮了吧</d><d p="22.65700,1,25,16777215,1539514051,0,191b94b4,6486426358120450">那么快就出了</d><d p="136.25200,1,25,16777215,1539514165,0,191b94b4,6486485911994370">哈哈哈哈哈哈</d><d p="104.49200,1,25,16777215,1539514133,0,191b94b4,6486469265850372">肝得漂亮</d><d p="170.99500,1,25,16777215,1539515809,0,3faf44d8,6487348309131264">这只竹鼠那么唱得那么好听，不如我们把她给关注一下吧</d><d p="121.33600,1,25,16777215,1539517173,0,2d09b3a5,6488063271239684">打破领零弹幕惨案</d><d p="119.85700,1,25,16777215,1539517156,0,2d09b3a5,6488054417063938">打破零弹幕惨案</d><d p="78.28600,1,25,41194,1539522852,0,12344e6a,6491040825999360">全程看天依</d><d p="127.59100,1,25,16777215,1539527688,0,cd1739e6,6493575944077314">厉害了</d><d p="5.21600,1,25,16777215,1539527966,0,8c73b242,6493721867583492">第三遍</d><d p="78.20600,1,25,16777215,1539533298,0,6cf30d8c,6496517139988484">好听</d><d p="97.72800,1,25,9033215,1539552244,0,cc089755,6506450342903810">棒棒棒！！！</d><d p="61.35800,1,25,16777215,1539575882,0,5bc262f8,6518843615215618">hhhhhhh</d><d p="155.44700,1,25,16777215,1539618539,0,4a025761,6541208330436608">哥们这是翻唱啊</d><d p="127.99400,1,25,16777215,1539660653,0,4086c741,6563287813062656">承包</d><d p="65.51300,1,25,16777215,1539664894,0,e88d14c2,6565511366180864">可爱(๑• . •๑)</d><d p="23.33900,1,25,16777215,1539670476,0,429fc237,6568437997371392">好听好听好听</d><d p="159.61800,1,25,16777215,1539670944,0,391afde2,6568683417632768">嘿嘿</d><d p="2.07600,5,25,16777215,1539692931,0,d1229bb9,6580211232014336">欢迎回来</d><d p="0.45600,5,25,16777215,1539692925,0,d1229bb9,6580208028090368">欢迎回来</d><d p="130.31300,1,25,16777215,1539693963,0,ddbb2fc6,6580752076505088">厉害了</d><d p="135.50900,1,25,16777215,1539702063,0,3e4b4ad1,6584998779944960">这只UP有点可爱，不如我们..........</d><d p="153.41400,1,25,16646914,1539704201,0,4df5cf6c,6586119954104322">饿了  有竹鼠外卖么</d><d p="73.16700,1,25,16777215,1539713952,0,ac30a3c8,6591232237633536">擦口水吧</d><d p="95.01600,1,25,16777215,1539732375,0,a0bba65,6600890989936640">阔爱</d><d p="13.49500,1,25,16777215,1539754932,0,edaf17b7,6612717652148224">来了</d><d p="73.66900,1,25,16777215,1539757166,0,7ea83eb,6613888753729536">好听</d><d p="85.26400,1,25,16777215,1539757178,0,7ea83eb,6613895029981184">烤了</d><d p="125.46200,1,25,16777215,1539757218,0,7ea83eb,6613916078571520">吃得多烤竹鼠咯</d><d p="96.59500,1,25,16777215,1539768716,0,4f8d054,6619944310538240">| ᐕ)୨可爱！</d><d p="17.76900,1,25,16777215,1539783433,0,ff00e6a3,6627660395970560">摸摸团砸狗头</d><d p="96.49600,1,25,16777215,1539841310,0,4bc1c431,6658004305313792">和天依不一样的风格，但是都很萌= =</d><d p="0.00000,1,25,16777215,1539861132,0,79c1eb20,6668396699582466">嗷呜</d><d p="159.00000,1,25,16777215,1539912564,0,2ee12a31,6695362045673472">很漂亮哦</d><d p="3.00000,1,25,16777215,1539913662,0,9f72adca,6695937667235840">rap太可爱了</d><d p="12.00000,1,25,16777215,1539914512,0,5b3611a9,6696383172575232">真的可爱啊</d><d p="115.00000,1,25,16777215,1539914633,0,dc49b54b,6696446775001088">好听！</d><d p="175.00000,1,25,16777215,1539915241,0,aec01b26,6696765460840450">这只竹鼠这么可爱不如我们。。</d><d p="88.00000,1,25,16777215,1539915849,0,dc49b54b,6697084186525696">这也太可爱了吧！</d><d p="91.00000,1,25,16777215,1539916336,0,a776570d,6697339623833600">烤竹鼠哈哈哈</d><d p="146.00000,1,25,16777215,1539926145,0,4cf6a8da,6702482094292992">哈哈哈哈哈哈哈哈哈哈</d><d p="110.00000,1,25,16777215,1539927610,0,2ee12a31,6703250623954944">前方高萌</d><d p="136.00000,1,25,16777215,1539934301,0,d8054187,6706758225494018">再来一遍！</d><d p="16.36400,1,25,16777215,1539943575,0,7c360033,6711620453531648">..666</d><d p="4.02500,1,25,16777215,1539948591,0,cd679fc2,6714250337714176">www</d><d p="138.48900,1,25,16777215,1539948728,0,cd679fc2,6714322319310848">可爱</d><d p="116.62200,1,25,16777215,1539948705,0,cd679fc2,6714310117031936">哇</d><d p="120.44600,1,25,16777215,1539950200,0,e03232f2,6715094052896768">rap满分</d><d p="6.57000,1,25,16777215,1540001114,0,a2381963,6741787699314688">我又回来了</d><d p="167.73500,1,25,16777215,1540005013,0,74185fe1,6743831892983808">团砸太可爱了！！</d><d p="178.26700,1,25,16777215,1540005024,0,74185fe1,6743837478748160">抱回家抱回家</d><d p="3.00000,1,25,16777215,1540006697,0,dc49b54b,6744714548609026">这版好听</d><d p="99.45300,1,25,16777215,1540006841,0,2d93938b,6744790228008960">更想吃了。</d><d p="8.12500,1,25,16777215,1540008329,0,5a088dfe,6745570280996864">欢迎回来</d><d p="165.00000,1,25,16777215,1540008764,0,38d0a899,6745798684966912">快破万啦</d><d p="165.00000,1,25,16777215,1540009858,0,570ec379,6746372256563200">白鼠鉴定完毕</d><d p="117.00000,1,25,16777215,1540021812,0,5b3611a9,6752639207342082">好可爱哈哈哈</d><d p="174.00000,1,25,16777215,1540022783,0,38d0a899,6753148753412096">快破万啦</d><d p="3.00000,1,25,16777215,1540029363,0,4cf6a8da,6756598112845824">竹鼠好可爱为什么要吃它</d><d p="65.00000,1,25,16777215,1540031680,0,dc49b54b,6757813111488512">今天华农兄弟不在家</d><d p="154.00000,1,25,16777215,1540031802,0,4cf6a8da,6757877227716610">你想怎么吃</d><d p="184.78900,1,25,16777215,1540033889,0,566bceb6,6758970962214912">不好，这只UP有危险，抄家伙上保护起来</d><d p="131.60800,1,25,16777215,1540048882,0,74185fe1,6766831797796864">肯定吃不消的呀！！WWW</d><d p="124.00000,1,25,16777215,1540052816,0,5b3611a9,6768894444306432">过于可爱</d><d p="170.60000,1,25,16777215,1540084804,0,1a966017,6785665351024640">百万调音师</d><d p="39.00000,1,25,16777215,1540099156,0,dc49b54b,6793189714821120">好听！</d><d p="24.00000,1,25,16777215,1540099277,0,4cf6a8da,6793253415813120">很漂亮哦23333</d><d p="104.00000,1,25,16777215,1540099641,0,a776570d,6793444283908098">素质三连了</d><d p="109.16700,4,25,16707842,1540099737,0,c3957d4c,6793494761308160">这只竹鼠，长那么大</d><d p="109.65500,4,25,16707842,1540099761,0,c3957d4c,6793507353133056">最喜欢吃，吃的又多</d><d p="116.05800,4,25,16707842,1540099859,0,c3957d4c,6793558638985216">烤竹鼠，闷竹鼠，红烧鼠，叫花鼠，花菇炖鼠</d><d p="148.38900,1,25,16777215,1540108853,0,81faed43,6798273709867008">真可爱</d><d p="163.80500,1,25,16777215,1540123062,0,981f0bbc,6805723500511232">好听警告</d><d p="94.30900,1,25,16777215,1540129708,0,e7bb9474,6809207959453696">加油哦</d><d p="14.25200,1,25,16777215,1540183736,0,74185fe1,6837534069882880">第n遍</d><d p="105.01400,5,25,16777215,1540183845,0,74185fe1,6837591425941504">前方rap可爱高能！</d><d p="67.34600,1,25,16777215,1540196267,0,6ddc4c59,6844104331231232">可爱</d><d p="16.19800,1,25,16777215,1540488141,0,6817b5,6997130165616640">再来一次</d><d p="18.49200,1,25,16777215,1540529997,0,33a15385,7019074764144642">a啊～</d><d p="17.35400,1,25,16777215,1540641766,0,6536aa0e,7077673693610048">一遍又一遍，遍了也不尽。</d><d p="85.54300,1,25,16777215,1540641876,0,6536aa0e,7077731252568064">这只竹鼠太胖了，红烧了。</d><d p="95.35900,1,25,16777215,1541136061,0,d0883da8,7336826688765952">这只竹鼠，既没有中暑，也没受伤，活着多没意思啊，不如我们。</d><d p="152.82800,1,25,16777215,1541313504,0,d84ae60a,7429857801666560">莫名的好萌...和天依不一样的萌</d><d p="104.64600,1,25,16777215,1541421696,0,566bceb6,7486581528592386">这只UP好可爱不让我们把她染成白色吧</d><d p="167.72500,1,25,16777215,1543284006,0,9839e407,8462968524636160">三连了</d><d p="80.88000,1,25,16777215,1544087122,0,da80881c,8884032584548352">超喜欢……</d><d p="68.34800,1,25,16777215,1544087109,0,da80881c,8884026032521216">喜欢喜欢！！声音好好听！！！</d><d p="156.90900,1,25,16777215,1545059171,0,78a2c1a9,9393666094268416">可耐</d><d p="4.89600,1,25,16777215,1546083956,0,2b48aa23,9930948766859264">天依</d><d p="66.89800,1,25,16777215,1546303214,0,93e4faf6,10045902828339202">嘎嘎嘎</d><d p="168.99200,1,25,16777215,1546741511,0,e9846945,10275697104257026">呜呜呜我哭了，太可爱了吧！</d><d p="50.72000,1,25,16777215,1548922795,0,6252fc73,11419318119563266">为什么莫名有种看起来像天依的感觉</d><d p="9.44000,1,25,16777215,1550407311,0,e54a4a79,12197631634178050">欢迎再次登陆</d></i>